{
    "Australia.jpeg": {
        "name": "JANE",
        "date_of_birth": "04/05/1991",
        "date_of_issue": "09/06/2022",
        "date_of_expiry": "09/06/2032",
        "authority": "CANBERRA",
        "nationality": ["AUSTRALIAN", "AUSTRALIA", "COMMONWEALTH OF AUSTRALIA"],
        "passport_type": "PD",
        "passport_number": "RD0117541"
    },
    "Australia.jpg": {
        "name": "JANE",
        "date_of_birth": "04/05/1991",
        "date_of_issue": "09/06/2022",
        "date_of_expiry": "09/06/2032",
        "authority": "CANBERRA",
        "nationality": ["AUSTRALIAN", "AUSTRALIA", "COMMONWEALTH OF AUSTRALIA"],
        "passport_type": "P",
        "passport_number": "RA0992035"
    },
    "Belgium.jpg": {
        "name": "EMMA",
        "date_of_birth": "18/12/1984",
        "date_of_issue": "28/03/2017",
        "date_of_expiry": "27/03/2022",
        "authority": "SPF AFFAIRES ETRANGERES",
        "nationality": ["BELGIAN", "BELGIUM", "BELGE"],
        "passport_type": "P",
        "passport_number": "LA000000"
    },
    "GuineaEcuatorial.jpeg": {
        "name": "ONDO MANGUE",
        "date_of_birth": "11/04/1984",
        "date_of_issue": "24/06/2018",
        "date_of_expiry": "23/06/2023",
        "authority": "ASONGA-BATA",
        "nationality": ["ECUATO GUINEAN", "EQUATORIAL GUINEA", "ECUATOGUINEANA", "REPUBLIC OF EQUATORIAL GUINEA"],
        "passport_type": "P",
        "passport_number": "P99990093"
    },
    "Iraq.jpeg": {
        "name": "MOHAMMED ABDULATEEF MOHAMMED",
        "date_of_birth": "31/07/1980",
        "date_of_issue": "05/10/2023",
        "date_of_expiry": "04/10/2027",
        "authority": "BAGHDAD",
        "nationality": ["IRAQI", "IRAQ", "REPUBLIC OF IRAQ"],
        "passport_type": "P",
        "passport_number": "R00000000"
    },
    "Latvia.jpeg": {
        "name": "LIENE MARA",
        "date_of_birth": "01/12/1986",
        "date_of_issue": "12/01/2015",
        "date_of_expiry": "12/01/2025",
        "authority": "PMLP RIGAS 1. NODALA",
        "nationality": ["LATVIAN", "LATVIA", "REPUBLIC OF LATVIA"],
        "passport_type": "P",
        "passport_number": "LV9000367"
    },
    "Sweden.jpeg": {
        "name": "SVEA",
        "date_of_birth": "21/08/1982",
        "date_of_issue": "01/01/2022",
        "date_of_expiry": "01/01/2027",
        "authority": "REGERINGSKANSLIET/UTRIKESDEPARTEMENTET",
        "nationality": ["SWEDISH", "SWEDEN", "SVENSK", "SVENSK/SWEDISH", "KINGDOM OF SWEDEN"],
        "passport_type": "PO",
        "passport_number": "XA0000004"
    },
    "Sweden.jpg": {
        "name": "SVEA",
        "date_of_birth": "21/08/1982",
        "date_of_issue": "01/01/2022",
        "date_of_expiry": "01/01/2027",
        "authority": "POLISMYNDIGHETEN",
        "nationality": ["SWEDISH", "SWEDEN", "SVENSK", "SVENSK/SWEDISH", "KINGDOM OF SWEDEN"],
        "passport_type": "P",
        "passport_number": "XA00000012"
    }
}
